{
  "title": "What Should We Do Every Day?",
  "background": "https://daily.ds106.us/wp-content/uploads/2015/09/new-tdc2.jpg",
   "attribution": "The official DS106 Daily Create logo! A response for <a href='https://daily.ds106.us/tdc4274/'>TDC4274</a>",
  "allwords": [
    {
      "words": [
        "Carp",
        "Coral",
        "Cheese",
        "Collapse",
        "Cheddar",
        "Chewy",
        "Color",
        "Cobble",
        "Copy"
      ]
    },
    {
      "words": [
        "Remix",
        "Ridicule",
        "Roll",
        "Rubber",
        "Really",
        "Revolution",
        "Red",
        "Resiprocate",
        "Ressurect",
        "Rebel"
      ]
    },
    {
      "words": [
        "Eat",
        "Early",
        "Enduring",
        "Everlasting",
        "Every",
        "Energize",
        "Ether",
        "Effort"
      ]
    },
    {
      "words": [
        "Art",
        "Apple",
        "Air",
        "All",
        "Austere",
        "Aunty",
        "Antagonist",
        "Absolute",
        "Arf"
      ]
    },
    {
      "words": [
        "Todd",
        "Totally",
        "Tease",
        "Testy",
        "Ten",
        "Twilight",
        "Toothy",
        "Terrible",
        "Tiny",
        "Tyrannosaurus",
        "Thoughtful"
      ]
    },
    {
      "words": [
        "Entire",
        "Elephant",
        "Etc",
        "Elbowed",
        "Enliven",
        "Ebony",
        "Eatery",
        "Eagle"
      ]
    }
  ]
}